nb_cron/__init__.py
nb_cron/_version.py
nb_cron/handlers.py
nb_cron/jobmanager.py
nb_cron/__pycache__/__init__.cpython-39.pyc
nb_cron/__pycache__/_version.cpython-39.pyc
nb_cron/__pycache__/handlers.cpython-39.pyc
nb_cron/__pycache__/jobmanager.cpython-39.pyc
nb_cron/static/common.js
nb_cron/static/cron.css
nb_cron/static/cron.html
nb_cron/static/menu.html
nb_cron/static/models.js
nb_cron/static/nb_cron.yaml
nb_cron/static/notebook.js
nb_cron/static/tree.js
nb_cron/static/urls.js
nb_cron/static/views.js
tests/__init__.py
tests/pyspark parameter test.ipynb
tests/python parameter test.ipynb
tests/spark parameter test.ipynb
tests/test_api.py
tests/test_notebook.py
nb_cron-0.4.4.dist-info/LICENSE
nb_cron-0.4.4.dist-info/METADATA
nb_cron-0.4.4.dist-info/WHEEL
nb_cron-0.4.4.dist-info/top_level.txt
nb_cron-0.4.4.dist-info/RECORD
