Metadata-Version: 2.1
Name: nb-cron
Version: 0.4.4
Summary: Manage your crontab from the Jupyter Notebook
Home-page: https://github.com/alexanghh/nb_cron
Author: alexanghh
Author-email: alexanghh@gmail.com
License-File: LICENSE
Requires-Dist: notebook (>=4.3.1)
Requires-Dist: croniter (>=1.0.13)
Requires-Dist: python-crontab (>=2.5.1)
